tentaclio_gs/__init__.py
tentaclio_gs/__main__.py
tentaclio_gs/clients/__init__.py
tentaclio_gs/clients/exceptions.py
tentaclio_gs/clients/gs_client.py
tentaclio_gs-0.0.1.dist-info/LICENSE.txt
tentaclio_gs-0.0.1.dist-info/METADATA
tentaclio_gs-0.0.1.dist-info/WHEEL
tentaclio_gs-0.0.1.dist-info/top_level.txt
tentaclio_gs-0.0.1.dist-info/RECORD
